{
  "heroes": [
    {
      "name": "gghrh",
      "descr": "hyhth",
      "element": "water",
      "id": 1668458284910
    },
    {
      "name": "nfgnf",
      "descr": "fhfh",
      "element": "wind",
      "id": 1668465552582
    },
    {
      "name": "апптртп",
      "descr": "ртпртпрт",
      "element": "earth",
      "id": 1668535017022
    },
    {
      "name": "gbrb",
      "descr": "bnyb",
      "element": "fire",
      "id": 1668535910406
    }
  ],
  "filters": [
    {
      "id": "all",
      "filter": "all",
      "lable": "Всі"
    },
    {
      "id": "fire",
      "filter": "fire",
      "lable": "Вогонь"
    },
    {
      "id": "water",
      "filter": "water",
      "lable": "Вода"
    },
    {
      "id": "wind",
      "filter": "wind",
      "lable": "Вітер"
    },
    {
      "id": "earth",
      "filter": "earth",
      "lable": "Земля"
    }
  ]
}